fdroidrepoapi/__init__.py
fdroidrepoapi/fetch.py
fdroidrepoapi/indexv2.py
fdroidrepoapi/keytool.py
fdroidrepoapi/metadata.py
fdroidrepoapi-0.1.1.dist-info/LICENSES/AGPL-3.0-or-later.txt
fdroidrepoapi-0.1.1.dist-info/LICENSES/CC0-1.0.txt
fdroidrepoapi-0.1.1.dist-info/METADATA
fdroidrepoapi-0.1.1.dist-info/WHEEL
fdroidrepoapi-0.1.1.dist-info/RECORD
